{
	"animations": [
		{
			"offsets": [
				0,
				0
			],
			"indices": [],
			"fps": 12,
			"anim": "idle",
			"loop": false,
			"name": "idle"
		},
		{
			"offsets": [
				0,
				0
			],
			"indices": [],
			"fps": 12,
			"anim": "singLEFT",
			"loop": false,
			"name": "left"
		},
		{
			"offsets": [
				0,
				0
			],
			"indices": [],
			"fps": 12,
			"anim": "singRIGHT",
			"loop": false,
			"name": "right"
		},
		{
			"offsets": [
				0,
				0
			],
			"indices": [],
			"fps": 12,
			"anim": "singDOWN",
			"loop": false,
			"name": "down"
		},
		{
			"offsets": [
				0,
				0
			],
			"indices": [],
			"fps": 12,
			"anim": "singUP",
			"loop": false,
			"name": "up"
		}
	],
	"no_antialiasing": false,
	"image": "characters/pearl",
	"position": [
		0,
		220
	],
	"healthicon": "mom",
	"flip_x": false,
	"healthbar_colors": [
		216,
		85,
		142
	],
	"camera_position": [
		0,
		0
	],
	"sing_duration": 4,
	"scale": 1
}